clickup_to_sqlite/__init__.py
clickup_to_sqlite/cli.py
clickup_to_sqlite/clickup_client.py
clickup_to_sqlite-0.2.0.dist-info/LICENSE
clickup_to_sqlite-0.2.0.dist-info/METADATA
clickup_to_sqlite-0.2.0.dist-info/WHEEL
clickup_to_sqlite-0.2.0.dist-info/entry_points.txt
clickup_to_sqlite-0.2.0.dist-info/top_level.txt
clickup_to_sqlite-0.2.0.dist-info/RECORD
