Metadata-Version: 2.1
Name: clickup-to-sqlite
Version: 0.2.0
Summary: Save data from ClickUp to a SQLite database
Home-page: https://github.com/gregmuellegger/clickup-to-sqlite
Author: Gregor Müllegger
License: Apache License, Version 2.0
Project-URL: Issues, https://github.com/gregmuellegger/clickup-to-sqlite/issues
Project-URL: CI, https://github.com/gregmuellegger/clickup-to-sqlite/actions
Project-URL: Changelog, https://github.com/gregmuellegger/clickup-to-sqlite/releases
Platform: UNKNOWN
License-File: LICENSE
Requires-Dist: sqlite-utils (>=2.4.2)
Requires-Dist: httpx
Requires-Dist: loguru
Requires-Dist: pydantic
Provides-Extra: test
Requires-Dist: pytest ; extra == 'test'
